LICENSE
MANIFEST.in
README.rst
gitreceive.py
setup.py
gitreceive.egg-info/PKG-INFO
gitreceive.egg-info/SOURCES.txt
gitreceive.egg-info/dependency_links.txt
gitreceive.egg-info/requires.txt
gitreceive.egg-info/top_level.txt