Metadata-Version: 1.1
Name: gitreceive
Version: 0.2.1
Summary: UNIX command-line tool for python line-based stream processing
Home-page: https://github.com/pahaz/git-receive
Author: Pahaz Blinov
Author-email: pahaz.blinov@gmail.com
License: MIT
Download-URL: https://pypi.python.org/packages/source/s/gitreceive/gitreceive-0.2.1.zip
Keywords: google spreadsheet api util helper
Platform: unix
Platform: macos
Platform: windows
Classifier: Development Status :: 3 - Alpha
Classifier: Intended Audience :: Developers
Classifier: Topic :: Utilities
Classifier: License :: OSI Approved :: MIT License
Classifier: Programming Language :: Python :: 3.4
Classifier: Programming Language :: Python :: 3.5
